{"hash":"51bbeda5eb65b5ea7b2427454d1b8e3b","data":{"html":"<span class=\"line\"><span style=\"--shiki-light:#24292E;--shiki-dark:#E1E4E8\">&#x3C;</span><span style=\"--shiki-light:#22863A;--shiki-dark:#85E89D\">video</span><span style=\"--shiki-light:#6F42C1;--shiki-dark:#B392F0\"> controls</span><span style=\"--shiki-light:#6F42C1;--shiki-dark:#B392F0\"> width</span><span style=\"--shiki-light:#24292E;--shiki-dark:#E1E4E8\">=</span><span style=\"--shiki-light:#032F62;--shiki-dark:#9ECBFF\">\"100%\"</span><span style=\"--shiki-light:#24292E;--shiki-dark:#E1E4E8\">></span></span><span class=\"line\"><span style=\"--shiki-light:#24292E;--shiki-dark:#E1E4E8\">  &#x3C;</span><span style=\"--shiki-light:#22863A;--shiki-dark:#85E89D\">source</span><span style=\"--shiki-light:#6F42C1;--shiki-dark:#B392F0\"> src</span><span style=\"--shiki-light:#24292E;--shiki-dark:#E1E4E8\">=</span><span style=\"--shiki-light:#032F62;--shiki-dark:#9ECBFF\">\"video.mp4\"</span><span style=\"--shiki-light:#6F42C1;--shiki-dark:#B392F0\"> type</span><span style=\"--shiki-light:#24292E;--shiki-dark:#E1E4E8\">=</span><span style=\"--shiki-light:#032F62;--shiki-dark:#9ECBFF\">\"video/mp4\"</span><span style=\"--shiki-light:#24292E;--shiki-dark:#E1E4E8\"> /></span></span><span class=\"line\"><span style=\"--shiki-light:#24292E;--shiki-dark:#E1E4E8\">&#x3C;/</span><span style=\"--shiki-light:#22863A;--shiki-dark:#85E89D\">video</span><span style=\"--shiki-light:#24292E;--shiki-dark:#E1E4E8\">></span></span><span class=\"line\"></span>","lang":"html"},"createdAt":1767144809947,"version":"1.0.0"}