{"hash":"55d7e80944cd3f6f99b2eefc06a63966","data":{"html":"<span class=\"line\"><span style=\"--shiki-light:#24292E;--shiki-dark:#E1E4E8\">{</span></span><span class=\"line\"><span style=\"--shiki-light:#24292E;--shiki-dark:#E1E4E8\">  async </span><span style=\"--shiki-light:#6F42C1;--shiki-dark:#B392F0\">generateBundle</span><span style=\"--shiki-light:#24292E;--shiki-dark:#E1E4E8\">(config) {</span></span><span class=\"line\"><span style=\"--shiki-light:#6A737D;--shiki-dark:#6A737D\">    // 生成额外的文件</span></span><span class=\"line\"><span style=\"--shiki-light:#D73A49;--shiki-dark:#F97583\">    await</span><span style=\"--shiki-light:#6F42C1;--shiki-dark:#B392F0\"> writeFile</span><span style=\"--shiki-light:#24292E;--shiki-dark:#E1E4E8\">(</span><span style=\"--shiki-light:#032F62;--shiki-dark:#9ECBFF\">'dist/sitemap.xml'</span><span style=\"--shiki-light:#24292E;--shiki-dark:#E1E4E8\">, sitemapContent)</span></span><span class=\"line\"><span style=\"--shiki-light:#24292E;--shiki-dark:#E1E4E8\">  }</span></span><span class=\"line\"><span style=\"--shiki-light:#24292E;--shiki-dark:#E1E4E8\">}</span></span><span class=\"line\"></span>","lang":"ts"},"createdAt":1767153011568,"version":"1.0.0"}