{"hash":"3c8bf6038ac30262d48ca1c19a14f1a9","data":{"html":"<span class=\"line\"><span style=\"--shiki-light:#D73A49;--shiki-dark:#F97583\">const</span><span style=\"--shiki-light:#005CC5;--shiki-dark:#79B8FF\"> pageData</span><span style=\"--shiki-light:#D73A49;--shiki-dark:#F97583\"> =</span><span style=\"--shiki-light:#6F42C1;--shiki-dark:#B392F0\"> usePageData</span><span style=\"--shiki-light:#24292E;--shiki-dark:#E1E4E8\">()</span></span><span class=\"line\"></span><span class=\"line\"><span style=\"--shiki-light:#24292E;--shiki-dark:#E1E4E8\">console.</span><span style=\"--shiki-light:#6F42C1;--shiki-dark:#B392F0\">log</span><span style=\"--shiki-light:#24292E;--shiki-dark:#E1E4E8\">(pageData.value.title)</span></span><span class=\"line\"><span style=\"--shiki-light:#24292E;--shiki-dark:#E1E4E8\">console.</span><span style=\"--shiki-light:#6F42C1;--shiki-dark:#B392F0\">log</span><span style=\"--shiki-light:#24292E;--shiki-dark:#E1E4E8\">(pageData.value.frontmatter)</span></span><span class=\"line\"><span style=\"--shiki-light:#24292E;--shiki-dark:#E1E4E8\">console.</span><span style=\"--shiki-light:#6F42C1;--shiki-dark:#B392F0\">log</span><span style=\"--shiki-light:#24292E;--shiki-dark:#E1E4E8\">(pageData.value.headers)</span></span><span class=\"line\"></span>","lang":"ts"},"createdAt":1767153010538,"version":"1.0.0"}