{"hash":"abf516107e5ea8afaa04a5a07fa1c3bf","data":{"html":"<span class=\"line\"><span style=\"--shiki-light:#6A737D;--shiki-dark:#6A737D\"># Create project directory</span></span><span class=\"line\"><span style=\"--shiki-light:#6F42C1;--shiki-dark:#B392F0\">mkdir</span><span style=\"--shiki-light:#032F62;--shiki-dark:#9ECBFF\"> my-docs</span></span><span class=\"line\"><span style=\"--shiki-light:#005CC5;--shiki-dark:#79B8FF\">cd</span><span style=\"--shiki-light:#032F62;--shiki-dark:#9ECBFF\"> my-docs</span></span><span class=\"line\"></span><span class=\"line\"><span style=\"--shiki-light:#6A737D;--shiki-dark:#6A737D\"># Initialize package.json</span></span><span class=\"line\"><span style=\"--shiki-light:#6F42C1;--shiki-dark:#B392F0\">pnpm</span><span style=\"--shiki-light:#032F62;--shiki-dark:#9ECBFF\"> init</span></span><span class=\"line\"></span>","lang":"bash"},"createdAt":1767153012806,"version":"1.0.0"}